alchemymodel_xlsx/__init__.py
alchemymodel_xlsx/const.py
alchemymodel_xlsx/exceptions.py
alchemymodel_xlsx/import_data_from_excel.py
alchemymodel_xlsx/template.py
alchemymodel_xlsx/to_csv.py
alchemymodel_xlsx/to_excel.py
alchemymodel_xlsx/utils.py
alchemymodel_xlsx-1.0.2.dist-info/METADATA
alchemymodel_xlsx-1.0.2.dist-info/WHEEL
alchemymodel_xlsx-1.0.2.dist-info/top_level.txt
alchemymodel_xlsx-1.0.2.dist-info/RECORD
